pyrage/__init__.pyi
pyrage/passphrase.pyi
pyrage/plugin.pyi
pyrage/py.typed
pyrage/ssh.pyi
pyrage/x25519.pyi
pyrage_stubs-1.3.1.dist-info/licenses/LICENSE
pyrage_stubs-1.3.1.dist-info/METADATA
pyrage_stubs-1.3.1.dist-info/WHEEL
pyrage_stubs-1.3.1.dist-info/top_level.txt
pyrage_stubs-1.3.1.dist-info/RECORD
